pydle_game/__init__.py
pydle_game/__main__.py
pydle_game/_stats.py
pydle_game/cli.py
pydle_game/game.py
pydle_game/data/words.json
pydle_game-1.0.2.dist-info/LICENSE
pydle_game-1.0.2.dist-info/METADATA
pydle_game-1.0.2.dist-info/WHEEL
pydle_game-1.0.2.dist-info/entry_points.txt
pydle_game-1.0.2.dist-info/top_level.txt
pydle_game-1.0.2.dist-info/RECORD
