Metadata-Version: 2.1
Name: pydle-game
Version: 1.0.2
Summary: Wordle in the terminal!
Home-page: https://gitlab.com/psalminen/pydle
Author: Paul Salminen
Author-email: paulsalminen@gmail.com
License-File: LICENSE
Requires-Dist: appdata
Requires-Dist: rich
Requires-Dist: termplotlib
